{
  "targetGrades": "고1",
  "targetRanks": "2~3등급",
  "curriculum_ref": "5월 정규수업",
  "lessonContent": {
    "review": [
      {
        "dataBlock": "| 도르래 수 | 장력 (N) |\n|---|---|\n| 1 | 10 |\n| 2 | 5 |\n| 3 | 3.33 |\n| 4 | 2.5 |",
        "question": "다음 표는 다양한 수의 도르래가 사용될 때 물체를 들어올리는 데 필요한 장력을 보여줍니다. 이 표를 바탕으로 도르래 수와 장력의 관계를 설명하고, 5개의 도르래를 사용했을 때 예상되는 장력은 얼마인지 구하세요.",
        "choices": [
          "2 N",
          "2.0 N",
          "2.2 N",
          "2.5 N"
        ],
        "answer": 2,
        "explanation": "도르래 수가 증가하면 장력은 그 반비례로 감소합니다. 5개 도르래를 사용할 경우 장력은 10 N / 5 = 2.0 N으로 계산됩니다.",
        "source": "2024년 평가원 6월 모의평가",
        "tactic": {
          "출제 의도": "도르래의 수가 늘어날 때 장력이 어떻게 변하는지 이해하도록 하기 위함입니다.",
          "함정 포인트": "장력 계산 시 반비례 관계를 잘못 이해할 수 있습니다.",
          "해결 전략": "반비례 관계를 이용하여 장력을 정확히 계산해야 합니다."
        }
      },
      {
        "dataBlock": "| 실험 조건 | 결과 (장력 변화) |\n|---|---|\n| 도르래 없음 | 10 N |\n| 도르래 1개 | 5 N |\n| 도르래 2개 | 3 N |\n| 도르래 3개 | 2.5 N |",
        "question": "표는 도르래의 사용에 따른 장력 변화를 보여줍니다. 도르래를 더 늘릴 경우, 각각의 장력이 어떻게 변할지 예측하고 6개의 도르래를 사용했을 때 예상되는 장력을 제시하세요.",
        "choices": [
          "1.6 N",
          "1.7 N",
          "1.8 N",
          "2.0 N"
        ],
        "answer": 3,
        "explanation": "도르래 수가 증가할수록 장력은 감소합니다. 6개를 사용할 경우, 10 N이 6으로 나누어져 1.67 N이 예상됩니다.",
        "source": "2024년 평가원 6월 모의평가",
        "tactic": {
          "출제 의도": "도르래 수와 장력 사이의 반비례 관계를 파악하는 능력 평가입니다.",
          "함정 포인트": "장력 감소 계산 시 정확도를 잊기 쉽습니다.",
          "해결 전략": "정확한 비율 계산으로 장력을 추정해야 합니다."
        }
      },
      {
        "dataBlock": "한 물체가 도르래 시스템을 통해 지면에서 5m 높이로 올라가면서 필요로 하는 장력은 다음과 같습니다: 1개 도르래 사용 시 10 N, 2개 도르래 사용 시 5 N, 4개 도르래 사용 시 2.5 N.",
        "question": "도르래 사용 수에 따른 장력 변화를 통해, 8개 도르래로 같은 물체를 들어 올릴 때 예상되는 장력을 계산해 보세요.",
        "choices": [
          "1.0 N",
          "1.25 N",
          "1.5 N",
          "2.0 N"
        ],
        "answer": 2,
        "explanation": "4개의 도르래 사용 시 장력이 2.5 N이므로, 8개의 도르래 사용 시 장력은 그 절반인 1.25 N이 됩니다.",
        "source": "2024년 평가원 6월 모의평가",
        "tactic": {
          "출제 의도": "도르래 사용 수 증가에 따른 장력 감소를 이해시키려는 문제입니다.",
          "함정 포인트": "절반으로 감소되는 장력을 직접적으로 연산하지 않을 가능성이 있습니다.",
          "해결 전략": "장력의 비례 관계를 명확히 이해하고 적용해야 합니다."
        }
      },
      {
        "dataBlock": "| 도르래 구성 | 장력 (N) | 물체의 질량 (kg) |\n|---|---|---|\n| 단일 도르래 | 10 | 2 |\n| 복합 도르래 | 5 | 2 |\n\n위 표는 두 종류의 도르래 시스템에서 동일한 질량의 물체를 들어올릴 때의 장력을 나타냅니다.",
        "question": "위의 표는 단일 도르래와 복합 도르래를 사용하여 동일한 질량의 물체를 들어올릴 때의 장력을 보여줍니다. 두 도르래 시스템 중 어느 것이 더 적은 힘으로 물체를 들어올릴 수 있으며, 이유는 무엇인가요?",
        "choices": [
          "단일 도르래가 더 적은 힘으로 물체를 들어올린다.",
          "복합 도르래가 더 적은 힘으로 물체를 들어올린다.",
          "두 도르래가 동일한 힘으로 물체를 들어올린다.",
          "도르래의 종류에 따라 장력은 변하지 않는다."
        ],
        "answer": 2,
        "explanation": "복합 도르래는 더 적은 장력으로 동일한 질량의 물체를 들어올릴 수 있습니다. 이는 복합 도르래가 도르래 개수를 늘려 물체의 무게를 나누어 분산하는 효과가 있기 때문입니다.",
        "source": "2024년 평가원 6월 모의평가",
        "tactic": {
          "출제 의도": "학생들이 도르래 시스템의 장력 원리를 이해하는지를 평가하기 위해 출제.",
          "함정 포인트": "단일 도르래와 복합 도르래의 차이를 혼동하여 같은 장력이 필요하다고 생각할 수 있음.",
          "해결 전략": "도르래의 구성에 따른 장력 분산 효과를 이해하고 이를 통해 복합 도르래가 장력을 줄이는 원리를 파악."
        }
      }
    ],
    "concept": {
      "guide": "핵심 데이터 프레임 해석을 시작합니다."
    },
    "core_exam": [
      {
        "dataBlock": "| 물체 질량 (kg) | 장력 (N) |\n|---|---|\n| 5 | 20 |\n| 10 | 40 |\n| 15 | 60 |",
        "question": "위 표는 동일한 도르래 시스템에서 물체의 질량에 따른 장력을 보여줍니다. 이 실험에서 장력이 물체의 질량에 비례하여 증가하는 것을 확인할 수 있습니다. 20kg의 물체를 같은 도르래에 매달았을 때 예상되는 장력은 얼마입니까?",
        "choices": [
          "70 N",
          "80 N",
          "90 N",
          "100 N"
        ],
        "answer": 4,
        "explanation": "장력은 물체의 질량에 비례하므로 5kg 증가할 때마다 20N 증가합니다. 따라서 20kg일 때는 100N의 장력이 작용합니다.",
        "source": "2024년 평가원 6월 모의평가",
        "tactic": {
          "출제 의도": "장력과 물체 질량 간의 비례 관계 이해",
          "함정 포인트": "비례 관계를 착각하여 잘못된 계산 수행",
          "해결 전략": "비례 관계를 기초로 증가율을 계산하고 이를 통해 장력을 예측"
        }
      },
      {
        "dataBlock": "| 시스템 | 장력 (N) |\n|---|---|\n| A (고정 도르래) | 30 |\n| B (이동 도르래) | 15 |",
        "question": "두 개의 다른 도르래 시스템 A와 B에 대해 장력을 비교하는 표입니다. 시스템 A는 고정 도르래이고, 시스템 B는 이동 도르래입니다. 동일한 힘으로 물체를 이동시킬 때, 어느 시스템이 더 적은 힘으로 동일한 작업을 수행할 수 있습니까?",
        "choices": [
          "시스템 A",
          "시스템 B",
          "두 시스템 동일",
          "정보 부족"
        ],
        "answer": 2,
        "explanation": "이동 도르래는 장력을 절반으로 줄여주므로 시스템 B가 더 적은 힘으로 작업을 수행할 수 있습니다.",
        "source": "2024년 평가원 6월 모의평가",
        "tactic": {
          "출제 의도": "이동 도르래의 기계적 이익 이해",
          "함정 포인트": "고정 도르래와 이동 도르래의 장력 혼동",
          "해결 전략": "각 도르래의 특성과 장력 차이를 이해하여 선택"
        }
      },
      {
        "dataBlock": "도르래 시스템: 고정 도르래와 이동 도르래로 구성된 시스템",
        "question": "고정 도르래와 이동 도르래가 모두 사용된 복합 도르래 시스템에서, 장력이 줄어드는 이유와 그 효과에 대해 설명하세요. 복합 도르래의 장점은 무엇입니까?",
        "choices": [
          "장력 증가, 작업 효율 증가",
          "장력 감소, 작업 효율 증가",
          "장력 증가, 작업 효율 감소",
          "장력 감소, 작업 효율 감소"
        ],
        "answer": 2,
        "explanation": "복합 도르래는 장력을 줄여주는 효과가 있어 보다 적은 힘으로 동일한 작업을 수행할 수 있게 합니다.",
        "source": "2024년 평가원 6월 모의평가",
        "tactic": {
          "출제 의도": "복합 도르래의 기능과 장점 이해",
          "함정 포인트": "장력 감소의 의미와 작업 효율의 혼동",
          "해결 전략": "도르래의 기계적 이점을 통한 장력 변화 이해"
        }
      },
      {
        "dataBlock": "| 도르래 수 | 물체 무게 (N) | 작용하는 장력 (N) |\n|---|---|---|\n| 1 | 60 | 60 |\n| 2 | 60 | 30 |\n| 3 | 60 | 20 |",
        "question": "표는 도르래의 수에 따른 물체의 무게와 장력을 나타낸 것입니다. 도르래의 수가 증가할수록 장력이 어떻게 변화하는지 설명하고, 도르래의 수가 4일 때 작용하는 장력을 예측하세요.",
        "choices": [
          "60N",
          "15N",
          "10N",
          "0N"
        ],
        "answer": 2,
        "explanation": "도르래의 수가 1 증가할 때마다 장력은 초기 값의 1/n로 줄어듭니다. 3개의 도르래일 때 장력은 20N이고, 4개일 때는 60/4 = 15N입니다.",
        "source": "2024년 평가원 6월 모의평가",
        "tactic": {
          "출제 의도": "도르래의 수에 따른 장력 변화를 이해시키기 위함입니다.",
          "함정 포인트": "도르래의 수가 증가함에 따라 장력이 줄어드는 비율을 헷갈릴 수 있습니다.",
          "해결 전략": "도르래의 수에 따른 장력의 역비례 관계를 계산해보세요."
        }
      },
      {
        "dataBlock": "| 물체 무게 (N) | 도르래 사용 여부 | 장력 (N) |\n|---|---|---|\n| 80 | 사용 안 함 | 80 |\n| 80 | 사용 | 40 |",
        "question": "위 표는 동일한 무게의 물체에 도르래 사용 유무에 따른 장력을 나타냅니다. 도르래를 사용할 경우 장력이 어떻게 변화하는지 설명하고, 도르래를 사용하지 않을 경우의 장력을 계산하세요.",
        "choices": [
          "40N",
          "80N",
          "20N",
          "0N"
        ],
        "answer": 2,
        "explanation": "도르래를 사용할 경우 장력은 물체 무게의 절반으로 줄어듭니다. 사용하지 않을 경우 물체 무게와 같은 80N입니다.",
        "source": "2024년 평가원 6월 모의평가",
        "tactic": {
          "출제 의도": "도르래 사용 유무에 따른 장력 변화를 이해시키기 위함입니다.",
          "함정 포인트": "도르래 사용 시 장력이 절반으로 줄어든다는 점을 간과할 수 있습니다.",
          "해결 전략": "도르래의 장력 감소 효과를 이용하여 물체 무게와 비교해 계산하세요."
        }
      },
      {
        "dataBlock": "| 도르래 배치 | 장력 (N) |\n|---|---|\n| 병렬 | 50 |\n| 직렬 | 25 |",
        "question": "표는 도르래의 배치 방식에 따라 장력이 어떻게 다른지를 보여줍니다. 병렬 배치와 직렬 배치에서의 장력 차이를 설명하고, 왜 이러한 차이가 발생하는지 분석하세요.",
        "choices": [
          "병렬 배치에서 장력이 더 크다.",
          "직렬 배치에서 장력이 더 크다.",
          "장력은 동일하다.",
          "장력은 배치와 무관하다."
        ],
        "answer": 1,
        "explanation": "병렬 배치에서는 중력이 여러 도르래에 분산되어 장력이 크게 나타납니다. 직렬 배치는 도르래 수만큼 나눠져 장력이 줄어듭니다.",
        "source": "2024년 평가원 6월 모의평가",
        "tactic": {
          "출제 의도": "도르래 배치 방식에 따른 장력의 변화를 이해시키기 위함입니다.",
          "함정 포인트": "범례 상의 배치 방식에 따른 장력 차이를 간과할 수 있습니다.",
          "해결 전략": "각 배치 방식에 따른 물리적 현상을 이해하고 장력을 비교하세요."
        }
      },
      {
        "dataBlock": "| 질량 (kg) | 각속도 (rad/s) | 형상 | 실험 결과 |\n|---|---|---|---|\n| 1 | 3 | 원형 | 20 N |\n| 2 | 2 | 원형 | 15 N |\n| 1 | 3 | 사각형 | 25 N |\n| 2 | 2 | 사각형 | 18 N |",
        "question": "위 실험 테이블은 도르래와 연결된 추의 질량과 각속도, 형상에 따른 장력을 보여준다. 질량과 각속도가 동일한 경우, 형상에 따라 장력에 어떤 영향을 미치는지 설명하시오. 이 실험에서의 결과를 바탕으로, 다음 중 올바른 설명을 고르시오.",
        "choices": [
          "형상이 달라도 장력은 동일하다.",
          "형상이 원형일 때 장력이 더 크다.",
          "형상이 사각형일 때 장력이 더 크다.",
          "형상의 차이는 장력에 영향을 미치지 않는다."
        ],
        "answer": 2,
        "explanation": "실험 결과 테이블을 보면, 질량과 각속도가 동일할 때 사각형 형상에서 장력이 더 큰 것을 알 수 있다.",
        "source": "2024년 평가원 6월 모의평가",
        "tactic": {
          "출제 의도": "도르래 시스템에서 형상에 따른 장력 변화를 이해시키기 위함.",
          "함정 포인트": "형상의 차이가 장력에 영향을 주지 않는다고 잘못 판단할 수 있음.",
          "해결 전략": "테이블의 실험 데이터를 분석하여 형상의 변화가 장력에 미치는 영향을 이해해야 함."
        }
      },
      {
        "dataBlock": "| 조건 | 힘 (N) |\n|---|---|\n| 도르래 1 | 50 |\n| 도르래 2 | 80 |\n| 도르래 3 | 100 |",
        "question": "세 개의 도르래 시스템에서 각 도르래에 걸리는 힘이 표와 같이 주어졌습니다. 도르래 시스템이 균형을 이루기 위해 각 도르래에 필요한 추가 힘을 계산할 때, 도르래 1과 도르래 3의 힘 차이가 가장 작게 되기 위한 추가 힘은 얼마인가요?",
        "choices": [
          "10 N",
          "20 N",
          "25 N",
          "30 N"
        ],
        "answer": 1,
        "explanation": "도르래 1과 3의 힘 차이를 최소화하려면 도르래 1에 20 N을 추가하여 두 도르래의 힘 차이가 30 N으로 줄어듭니다.",
        "source": "2024년 평가원 6월 모의평가",
        "tactic": {
          "출제 의도": "도르래 시스템의 장력 균형 파악",
          "함정 포인트": "무게 중심을 고려하지 않음",
          "해결 전략": "도르래 간 힘 차이를 분석하여 최소화"
        }
      },
      {
        "dataBlock": "| 도르래 수 | 필요 장력 (N) |\n|---|---|\n| 1 | 20 |\n| 2 | 35 |\n| 3 | 50 |",
        "question": "단일 도르래 3개가 각각 다른 장력을 필요로 하는 실험 시스템이 있습니다. 각각의 도르래가 동일한 물체를 들어 올리기 위해 필요한 장력이 주어졌을 때, 가장 효율적으로 물체를 들어 올리려면 어떤 도르래를 먼저 사용해야 할까요?",
        "choices": [
          "도르래 1",
          "도르래 2",
          "도르래 3",
          "어느 도르래도 무관하다"
        ],
        "answer": 3,
        "explanation": "가장 작은 장력으로 시작하여 점차 증가시키는 것이 효율적이므로, 도르래 1을 먼저 사용합니다.",
        "source": "2024년 평가원 6월 모의평가",
        "tactic": {
          "출제 의도": "장력을 최소화하는 방법 선택",
          "함정 포인트": "큰 장력의 도르래부터 사용함",
          "해결 전략": "표에서 최소 장력 값을 찾고 적용"
        }
      },
      {
        "dataBlock": "| 물체 | 무게 (kg) | 걸리는 총 장력 (N) |\n|---|---|---|\n| 물체 A | 5 | 75 |\n| 물체 B | 10 | 150 |",
        "question": "다음 표는 두 개의 물체 A와 B가 각각 도르래 시스템에서 들어 올려질 때 걸리는 총 장력을 나타냅니다. 물체 A를 도르래 시스템에서 들어 올릴 때 필요한 최소 도르래 수는 몇 개인가요?",
        "choices": [
          "1개",
          "2개",
          "3개",
          "4개 이상"
        ],
        "answer": 2,
        "explanation": "물체 A의 무게를 고려하여 각각의 도르래가 처리할 수 있는 장력을 나누어 사용해야 하므로 최소 두 개의 도르래가 필요합니다.",
        "source": "2024년 평가원 6월 모의평가",
        "tactic": {
          "출제 의도": "도르래 수에 따른 장력 분배 이해",
          "함정 포인트": "개별 장력 인식 부족",
          "해결 전략": "각 도르래의 장력 분배를 통해 효율적 사용"
        }
      }
    ],
    "error_pattern": {
      "summary": "해당 단원의 함정 선지를 파훼합니다."
    },
    "application": [
      {
        "dataBlock": "| 물체 질량 (kg) | 도르래 A | 도르래 B |\n|---|---|---|\n| 5 | 8 N | 10 N |\n| 10 | 16 N | 20 N |\n| 15 | 24 N | 30 N |",
        "question": "위의 표는 각각의 질량을 가진 물체가 도르래 A와 B에 걸렸을 때의 장력을 나타내고 있습니다. 이 실험에서 도르래의 효율에 영향을 줄 수 있는 요인으로 적절하지 않은 것을 고르세요.",
        "choices": [
          "물체의 질량",
          "도르래의 마찰",
          "도르래의 반지름",
          "물체의 재질"
        ],
        "answer": 4,
        "explanation": "물체의 재질은 도르래의 효율에 직접적인 영향을 미치지 않습니다. 대신 장력에 영향을 줄 수 있는 요인은 물체의 질량, 도르래의 마찰, 도르래의 반지름 등입니다.",
        "source": "2024년 평가원 6월 모의평가",
        "tactic": {
          "출제 의도": "장력과 도르래의 관계를 이해하고 적용하기 위함입니다.",
          "함정 포인트": "물체의 재질이 영향을 미칠 것으로 착각할 수 있습니다.",
          "해결 전략": "도르래 및 장력에 영향을 미칠 수 있는 물리적 요인을 파악하세요."
        }
      },
      {
        "dataBlock": "| 도르래 종류 | 물체 질량 (kg) | 장력 (N) |\n|---|---|---|\n| 단독 도르래 | 10 | 40 |\n| 이중 도르래 | 10 | 20 |",
        "question": "단독 도르래와 이중 도르래를 사용할 경우, 10 kg의 물체에 발생하는 장력이 서로 다른 이유를 설명하세요. 아래 요인 중 가장 관련이 없는 것을 고르세요.",
        "choices": [
          "도르래의 종류",
          "장력의 방향",
          "도르래의 효율",
          "중력 가속도 값"
        ],
        "answer": 4,
        "explanation": "중력 가속도 값은 도르래가 제공되는 방식과는 별개로 일정하므로, 장력을 비교하는 데 영향이 없습니다.",
        "source": "2024년 평가원 6월 모의평가",
        "tactic": {
          "출제 의도": "도르래의 종류에 따른 장력 차이를 이해하도록 하는 것입니다.",
          "함정 포인트": "중력 가속도 값이 영향을 미칠 것이라고 생각할 수 있습니다.",
          "해결 전략": "도르래의 기계적 이점과 효율성을 고려하여 비교하세요."
        }
      },
      {
        "dataBlock": "| 도르래 시스템 | 물체 무게 (N) | 요구되는 힘 (N) |\n|---|---|---|\n| 단독 | 100 | 100 |\n| 이중 | 100 | 50 |",
        "question": "위의 데이터는 도르래 시스템에 따른 물체를 들어 올리는 데 요구되는 힘을 나타냅니다. 이중 도르래를 사용할 때의 이점으로 올바르지 않은 것을 고르세요.",
        "choices": [
          "필요한 힘의 감소",
          "속도의 증가",
          "작업의 효율 상승",
          "장치의 안정성 증가"
        ],
        "answer": 2,
        "explanation": "이중 도르래는 필요 힘을 줄이는데 주 목적이 있으며, 작동 속도는 증가하지 않습니다.",
        "source": "2024년 평가원 6월 모의평가",
        "tactic": {
          "출제 의도": "도르래 시스템의 효율성을 이해하고 비교해보는 것입니다.",
          "함정 포인트": "이중 도르래가 속도에도 영향을 미친다고 생각할 수 있습니다.",
          "해결 전략": "기계적 이점 및 효율성 관련 요인을 정확히 파악하세요."
        }
      },
      {
        "dataBlock": "| 실험 조건 | 추의 질량 (kg) | 도르래의 개수 |\n|---|---|---|\n| A | 1 | 1 |\n| B | 1 | 2 |\n| C | 2 | 1 |\n| D | 2 | 2 |",
        "question": "위의 표는 장력과 도르래 실험의 조건을 설명합니다. 각 조건에서 추를 들어올리는 데 필요한 힘을 비교할 때, C 조건에서 필요한 힘이 가장 큰 이유를 설명하세요.",
        "choices": [
          "A 조건이 가장 작은 힘이 필요하다.",
          "B 조건은 C 조건보다 더 큰 힘이 필요하다.",
          "C 조건은 질량이 가장 큰 추를 사용하기 때문이다.",
          "D 조건은 도르래가 많아 더 큰 힘이 필요하다."
        ],
        "answer": 3,
        "explanation": "조건 C는 A에 비해 질량이 두 배 크며, 도르래 개수는 같아 장력 감소 효과 없이 그대로 적용됩니다.",
        "source": "2024년 평가원 6월 모의평가",
        "tactic": {
          "출제 의도": "장력과 도르래의 기본 원리 이해를 평가하기 위함.",
          "함정 포인트": "도르래의 개수와 장력의 관계를 오해할 수 있음.",
          "해결 전략": "질량과 도르래의 역할을 각각 독립적으로 분석해보세요."
        }
      },
      {
        "dataBlock": "| 도르래 시스템 | 필요한 장력 (N) | 사용된 도르래 개수 |\n|---|---|---|\n| 시스템 1 | 100 | 1 |\n| 시스템 2 | 50 | 2 |\n| 시스템 3 | 33.3 | 3 |\n| 시스템 4 | 25 | 4 |",
        "question": "본 표는 도르래 개수에 따른 장력 감소 효과를 나타냅니다. 시스템 4가 시스템 1에 비해 얼마나 더 적은 장력이 필요한지, 그 비율을 계산하여 설명하세요.",
        "choices": [
          "1/2",
          "1/3",
          "1/4",
          "1/5"
        ],
        "answer": 3,
        "explanation": "시스템 4는 시스템 1의 장력 100 N에 비해 25 N이므로, 1/4인 4분의 1의 장력만 필요합니다.",
        "source": "2024년 평가원 6월 모의평가",
        "tactic": {
          "출제 의도": "장력 감소 효과를 수리적으로 이해시키기 위함.",
          "함정 포인트": "단순 비율 계산을 실수할 수 있음.",
          "해결 전략": "각 시스템 간의 장력을 구체적으로 비교하여 비율을 명확히 검토하세요."
        }
      }
    ]
  },
  "roundMeta": {
    "title": "[고1 2~3등급] 5월 전용 수업",
    "intro": "본 물리학 수업은 [고1 2~3등급] 정규 5월 2주차 2회차입니다. 핵심: \"장력과 도르래 문제\""
  }
}