{
  "schemaVersion": "2.0",
  "sourceQuestionPdf": "\\\\Subitmainpc\\수학의 빛 사무폴더\\09.새 교과과정 자료\\01.자료_수학1\\교재_시중교재\\블랙라벨_수학1-PDF\\02 방정식과 부등식\\06여러가지 방정식.pdf",
  "sourceAnswerPdf": "\\\\Subitmainpc\\수학의 빛 사무폴더\\09.새 교과과정 자료\\01.자료_수학1\\교재_시중교재\\블랙라벨_수학1-PDF\\02 방정식과 부등식\\06여러가지 방정식_답안지.pdf",
  "curriculum": {
    "grade": "고1",
    "semester": "1학기",
    "course": "공통수학1",
    "unit": "방정식과부등식",
    "score": 9
  },
  "difficulty": "하",
  "items": [
    {
      "number": 1,
      "questionImage": "questions/06여러가지 방정식_q001.webp",
      "solutionRaw": "=0 \n(i), (ii), (iii)oJIAl \n/(l) =/(2) =0, /(3) \n... /(1)+/(2)+/(3) \nrr}eJ-Al /(n) \n1885=6X314+ \n711\"i'-7f %l\"i'-~ {'~P;J~6.l~ iiH7f l-!2iOII:'1 l+!2i.s:. 2­\n~~ol§Hor.:t!, LfD1AI ~ acf ~ 2-ilf 711\"i'-~ B7II~ \nol§etCf. \na, b, c7} 1l4-,{] {l-~poJ~6J \n~ol 1-!2ioj~ l+!2i.£oj \nLj-u-]Aj ~ 2 ~ aeJ-otI{l \"'-\"U·~.'/~ \noJj .9]o}O:j \n(1 +!2i) + (l-!2il +a= \na=-(2+a) \n(1 +!2i)(I-!2i) + (1 + !2i) Xa+a x (1-!2il =b \noJjJ--j b=2a+3 \n(1 +!2i) (l-!2i)a= -coJjAl \nc=-3a \n?Ol~ -'-j'-tlJ;;>:.J<-1 \no\n] 512 \n~ ~~~.... \n~','~,,-: ~r::Al b' '8 20] 5'1~ 27H.9] -l.!...!j~* \nrr}eJ-Al -%-R~ ao]~ oj~}tlJ;;>:'J6J \n~~~::c}. \n... a\n2\n+aa+2=0 ...... @ \n@oJ] T:Jl'fjo}I{l a\n2\n-(2+a)a+2=0 \n-2a+2=0 ... a=l \n©oJj T:Jl'fjotli'i \na 3, b=5, c=-3 \n... abc=(-3)X5X(-3)=45 @) 45 \nt.L.--,,*--.Lj B \n-­200m-­o 100m \noj n:Jl , \n...... 6) \noJjAl 0JJt!~ A~*O}li'i \n90000 \n...... (9 \n(x+2y) (5x-4y) =0 \n... y= (.,' x>o, y>O) \n°l~~ 6)on \n£x\n2\n+30000=0\n16 \n\n9 2\n\nWX =30000, \n... x= 400 (.,' x>O) \n=200/3 (m/~)o]jl, \n(m/~)olcl-. \n@) if :200/3, ~ : 250/3 \nmn-5m+4n=100on\nA\nl \n\nmn-5m+4n-20=80 \n\n... (m+4)(n-5) =80 \n\n01 lIJl , m, \n\nm+42} n-5:: \n\n-4::;n-5::;15ojc}. \n\nrr}eJ-Al 'ii:-)+\"\"J (m+4, n-5) (8, 10), \n\n(10, 8), (16, 5), (20, 4) oju:Jj.9] 'ii:-Al'i \n\n(m, n)~ (4, 15), (6, 13), (12, 10), (16, 9)ojc}. \n\n~, ±::ct~ 1i1~oN=-'ii:-Al»-J (m, n).9] 40jc}. \n\nn~ l¥EJ 20J.,'l7.1.9] \n@)4 \n01 ~ 01 *\" E I) 58 \nl@ 2@ \n3@ \n060 I \n\n\n~AtZ,f113 £~9.J §Ol~ {ljg .:J.EjOjIAj ~J:lE ~Xi121El\" \n¥ ~Z,f,gZ,f113ol gra'i'J~ Ol~otol ~J:lE .!?ffi~ ol§~,gZ,f \n\\;llOl7f 10'i'J~ Ol~otol ~~~~ Aih~ tg \na9.J ~~.::;:te.fc.I-. \nD \nA \n\"flS'.J .::LifloJlAl zJ::z{AJ::z{~ CEDQ} \nAB=ED=a, LCDE= LCBA=90\", \nLECD= \n:. x= \nl:l.CAES'.J \\illo]-t-lOo].EI.i2. \n\nl:l.CAE= 1 x a x -=······~-=-=10 \n\na\n3\n+64a-3Z0=O, (a-4) (a\n2\n+4a+80) =0 \n01rrJ1, a\n2\n+4a+80=(a+Z)2+76> \na=4 \n.£z..l?j%S'.J ¥II17~ 108°j.EI.i2. \n[X(X+3)+ ](X+l)=108 \n[x(x+3) +Zx+3j(x+1) 108 \n(x\n2\n+5x+3)(x+1) 108 \nx \n3\n+6x\n2\n+8x-105=O \n(x\n2\n+9x+35)=0 \n01rrJ1, x \n2\n+9X+35=(x+ \n...§2..> \n\\ \n4 \nx=3 \n..g~ ~¥ !i!J1 ~OiAi ~g \n~ Ai121~ q§ ~~~g \n871IOjIAj .::;:tEl\" ~~~~~2.1 ~1Fa .::;:t~q. \n;5E .:l ~~.£gr~ ~~-6.{ \n~~;g~ ol~ofOj ;J':i~OjI ~01E ~ \n~... ~~~~.,..,...., \"'~\"\"~'~'~~'~'~~~'.~~\"'\" \ny=-Z, \n~.0~ (-2Z+X= -3 li1~AjZlq. \n::;, -Zb=4\n0 \n·.EI.i2. b=-2 \n1f*5LJl \nM..:::~x.tR'i'l \nx=-l, \nz=l~ \n( -2Z+X~-3 \nli1';Al z!q. \n::;, -a+3=loJ1\nA\nl a=2 \n2x+y=1 \n\n2y+z=4 \n\n-2z+x=-3 \n\nZx 6)+(9% \n4x+z=6 ......@ \n2X~ \n9x=9 :. x=l \ny=-1,z=2 \n\nrr}c}Al a=l, 13= 1, r= \n\na+13+r=2 \\ID ® \n\nr 3x-y+2z=4 \nl\nx-Zy+2z=1 \n......0;) \nax+ay-Zz=O \n...... © \nZx+y=3 \ny=3-Zxol.EI.i2. \n(a+ l)x+ (a-2) (3-Zx) \nax+x+3a-2ax-6+4x=1 \n:. (5-a)x=7-3a \nolrrJ1, ~if:polJ~.61S'.J -EARi>~Al \n5-a=OolJl, 7-3a:;l::Ooloj0J: \n:. a=5",
      "solutionDisplay": "식 정리 후 iii)oJIA1 형태를 이용한다.",
      "formulaLatex": [
        "iii)oJIA1",
        "1)+/(2)+/(3)",
        "eJ-A1",
        "1885=6X314+",
        "iiH7f",
        "LfD1AI",
        "2-i1f",
        "B7II",
        "114-",
        "Lj-u-]Aj",
        "aeJ-otI",
        "a=-(2+a)",
        "2i)(I-",
        "Xa+a",
        "oJjJ--j",
        "b=2a+3",
        "2i)a=",
        "coJjA1",
        "c=-3a",
        "aa+2=0",
        "2+a)a+2=0",
        "2a+2=0",
        "fjot1i",
        "abc=(-3)X5X(-3)=45",
        "200m-",
        "oJjA1",
        "x+2y)",
        "5x-4y)",
        "30000=0",
        "o1c1-",
        "mn-5m+4n=100on",
        "mn-5m+4n-20=80",
        "m+4)(n-5)",
        "m+42",
        "40jc",
        "f113",
        "Xi121E1",
        "f113o1",
        "11O17f",
        "Lif1oJ1A1",
        "AB=ED=a",
        "LCDE=",
        "LCBA=90",
        "LECD=",
        "i11o]-t-1Oo]",
        "CAE=",
        "64a-3Z0=O",
        "4a+80)",
        "4a+80=(a+Z)2+76",
        "X(X+3)+",
        "X+1)=108",
        "x(x+3)",
        "Zx+3j(x+1)",
        "5x+3)(x+1)",
        "8x-105=O",
        "9x+35)=0",
        "9X+35=(x+",
        "Ai121",
        "871IOjIAj",
        "2Z+X=",
        "AjZ1q",
        "Zb=4",
        "1f*5LJ1",
        "2Z+X",
        "a+3=1oJ1",
        "2x+y=1",
        "2y+z=4",
        "2z+x=-3",
        "4x+z=6",
        "9x=9",
        "a+13+r=2",
        "3x-y+2z=4",
        "x-Zy+2z=1",
        "ax+ay-Zz=O",
        "Zx+y=3",
        "y=3-Zxo1",
        "3-Zx)",
        "ax+x+3a-2ax-6+4x=1",
        "5-a)x=7-3a",
        "5-a=Oo1J1",
        "7-3a"
      ],
      "graphExpressions": [
        "2x+y=1",
        "Zx+y=3",
        "y=3-Zxo1"
      ],
      "matched": true,
      "matchScore": 1
    },
    {
      "number": 2,
      "questionImage": "questions/06여러가지 방정식_q002.webp",
      "solutionRaw": "J--oj-lfl \nD= 5x+8) \n10x+25-4x\n2\n+20x-32 0 \n10x+7::;O, (3x-7) 1)::;0 \nl<x<l\n-\t-    3 \nx= ~ \nJLt+~ \n3 9 \n\n4  V \n4­\n(\nt-\n3\n) \n=0 :. t=3 (:g-c.:) \n.  7\n:. y=z= \n. 3' y=z= \n~F!1l1 )!j\"~6j x\"-l =O£I 01-2 aOlI cW~! tl:71I6j~ -T'e!er. \n~;~1l1: 1101 31<, 31<+ 1, 31<+2~ [8£1 f(n)Qj y~-T'~fCr. \n.O\"'f!?ll \nrlJAa61 x \n3\n-1=0. \nl)(x'+x+l) \n\n01 aol~ \n\na:J=l, 1=0 \n\n:. fen) (a\"+a)\"+(a\n2\n+1 1)\" \n\n(-1)\"+( ( \n(1) \tn=3k (k=l, 2, 3, ... ) ~ rrJ1, \n!(3k) =( -(-a)'Ii+ ( \n( 1) \n3\nl\"+{( -a)'Y'+[( \n(-1)\"+(-1 (1)\" \n=3x (-1)\" \n(ti) n 3k+1 (k=O, 1, 2, ... ) ~ rrJ1, \n!(3k+ 1) (1 (_a)3HI+ ( \n( If-a( 1 1)\" \n(-1) =0 \n\n67H.9] \n/(1) +/(2) + ... +/( 1885) \n1885)=0 \n(iii) n=3k+2 \n1, 2, ... ) °d n:Jl, \n( _(ij3H2 \n/(3k+2) \nl)\"+a( -1)\"",
      "solutionDisplay": "식 정리 후 5x+8) 형태를 이용한다.",
      "formulaLatex": [
        "5x+8)",
        "10x+25-4x",
        "20x-32",
        "10x+7",
        "3x-7)",
        "JLt+",
        "01-2",
        "aO1I",
        "f(n)Qj",
        "r1JAa61",
        "1)(x^2+x+1)",
        "fen)",
        "a+a)+(a",
        "n=3k",
        "3k+1",
        "a)3HI+",
        "If-a(",
        "1885)=0",
        "n=3k+2",
        "3k+2)"
      ],
      "graphExpressions": [],
      "matched": true,
      "matchScore": 1
    },
    {
      "number": 6,
      "questionImage": "questions/06여러가지 방정식_q006.webp",
      "solutionRaw": "ofl LJl 'fli5}li:! \n+2-k=0 :. x'-x+k-2=0 \nq-l.2.] 0l~t°J:Aa610l 11-2-* ?£71 q.j(';HA1;: \nD= ( 1)2-4(k-2) 2::0oflAl \n4k2:: -9 \n:. k<~\n-4 \nq.j~ 114' k.2.] ~'1!«~ ~ o]r:t. \n...... C:Q \n...... © \n~ @Oil LJl'fli5}li:! \nx+(k+1)y=0 \no]~ \n(1-k\n2\n-k)x=0 \n1-k'-k=001o-J\no\nl= \n1=0 \n.'. k=-Jt}5 \n-%l. ~~®olr:t. \n@@ \n0]~}oJ;Aa61 \n=0.2.] A1.£ r:t~ -i'--2-\n0\n1 \na, /30] \n~0];i.P'1:)-;Aa61.2.] \n7-114'.2.] f!-7-11oj] .2.] ii}o:j \na+/3 -a, \n{[~}oJ;Aa61 \n),1'£ r:t~ ),~ -2-\n0\n1 a, /3, \n7-114'.2.] f!-7-11ofl .2.]i5}o:j \na/3y=36 \nLJlOJi5}li:! \n-a+r=O :. y=a \na/3+ /3y+ya=aoflAl a/:1+y( a+(J) =aol~ \n~'a, \nb-a'=a \na/3r=36ofl \nab=36 \nab=360il \na(a'+a) =36, \n(a-3) (a'+4a+ 12) =0 \n:. a=3 (\": \n12 \n.:L~ ~ .:z.if:j0i]A1 -\"J/ r\"r/ r'C<> \n'ii~.2.] ~oL \nx, \nyc.} i5}li:! \nr\nx2\n+\nl \n=26' \n1(x-4)+(y--4) =26 \nC:QOiJAi y=34-xO]~ \nx'+ (34-x )2=26', \n1156-6Sx+x'=676 \nx'-34x+240=0,",
      "solutionDisplay": "식 정리 후 f1i5 형태를 이용한다.",
      "formulaLatex": [
        "f1i5",
        "2-k=0",
        "x^2-x+k-2=0",
        "Aa6101",
        "11-2-*",
        "1)2-4(k-2)",
        "0of1A1",
        "x+(k+1)y=0",
        "k)x=0",
        "k=001o-J",
        "k=-Jt",
        "Aa61",
        "7-114",
        "7-11of1",
        "a/3y=36",
        "a+r=O",
        "3y+ya=aof1A1",
        "a/3r=36of1",
        "ab=36",
        "ab=360i1",
        "j0i]A1",
        "1(x-4)+(y--4)",
        "y=34-xO]",
        "34-x",
        "2=26",
        "1156-6Sx+x^2=676",
        "x^2-34x+240=0"
      ],
      "graphExpressions": [
        "x+(k+1)y=0",
        "a/3y=36",
        "y=34-xO]"
      ],
      "matched": true,
      "matchScore": 1
    },
    {
      "number": 9,
      "questionImage": "questions/06여러가지 방정식_q009.webp",
      "solutionRaw": "Qj ~Jl1 oJ1 .Qj <>}o:j \na+l=-p, a=q \n3a+1=-q, 3a=p \nC9<>fl \nA\nl a+ 1=­\n1\n4a=-1 \n:. a= 4\" \na=qojE'£ p= \n,q \nx =16 \n@ 16 \nI. 017:}tlJ~61.Qj -2'2j-7j19-.Qj ~7jjoJj \nax\n2\n+bx+c=0.Qj \n~ oj4. \nJ..-l£~4. \n({l-) \nL. oj7.}BJ~61.Qj 1J9-~ a7} \n'5}J?:! \naa\n2\n+ba+c=0 ......6) \naa\n2\n+Zba+c=0 \n'5}J?:! ba=Ooj.Jl, ac> a*O \n:. b=O \n~~\",\"c.r·:=±-tloJ1.2.i?o14. \nac>ool \nrr}t'.}.kl ac>OolJ?:!.!f-°17.}tlJ?:a61~ \n?t;<1 ({l-) \nc 0l7z}tlJ'~61 ax\n2\n+Zbx+c=ool \"01Zg \nD =b2-ac<0\n4 \n/\".\",r-\",,~' \nax\nI, L, \nax\n2\n+bx+c=0.Qj jj.j-\"3-6J·;;;;\" D\nl \no1 \nb\n2\n-ac<O \n2\n+bx+c=O.5:. \"01Zg \nc\no",
      "solutionDisplay": "식 정리 후 a+1=-p 형태를 이용한다.",
      "formulaLatex": [
        "a+1=-p",
        "3a+1=-q",
        "3a=p",
        "4a=-1",
        "2j-7j19-",
        "bx+c=0",
        "1J9-",
        "ba+c=0",
        "Zba+c=0",
        "Zbx+c=oo1",
        "01Zg",
        "b2-ac",
        "j-3-6J",
        "bx+c=O"
      ],
      "graphExpressions": [],
      "matched": true,
      "matchScore": 1
    },
    {
      "number": 10,
      "questionImage": "questions/06여러가지 방정식_q010.webp",
      "solutionRaw": "24) =0 \n:. x=10 EE.;: x=24 \n.   Jx=10 {X=24L.\n..  l EE.­\ny=24 y=10L­\n@ 14\nu:f2.}Ai -'Q zr~ 7£l -i'-~.2.] ~0].2.] \n~~Ai]E A, B, C.2.] \n;g.R~~~17} 42:mol~ \n612 R7}46~ol~ \ni5}li:! 2x-2z= -4 ... z=x+2 \n056 I \n\n\n®% 6), CSP11 III ~<>~o:j ?:a \nZx+y=ZO, \t\n:. z=7 \n'i'l7cr.Jl A oJ1 AJ;<r\n7\t\n1\nr \no]t'.} '5~.Jl, ~, \na, b, ct'.} '5r;;z}. \n(7})ojjJ'i ~2j-\n6a+6b=1 :. a+b= \n(L})oj].kl ~~ 15.kjzt, \n\n-a-}9:l.~ \n\n15a+5b -10c= 1 \n••.•. •Ci;!\n:. 3a+b-Zc= ~ \n(q)ojj.ki ~, g, '8~ \nlZa+ 1Zb-12c=1 \n:. a+b-c= A \n'5}J?:! c= lIZ \n\nCi;!oJj III '?J '5}o:j ?:a tj-a-}J?:! \n\n11\n\n3a+b=3il \n'tl'El'5}o:j *J?:! a= 110 ' b= \n~~ ~g-a-};<j '5}o:j 'i'l 7cr \nAoJj AJ;<~7~~9;: 1:ij 10.k1zroj4. \n@@ \n: ZOjE'£ \nx: \n:  Z :. Zx=3y \nAQ1DoJj.kl \tAD=x, \n\n-Z \n\nP\n1\nQ2\nD\noJ1.k1 P\n1\nD=\"3\nx\n, \n-1 \t­\nP\n2\nCDoJ1.kl P2D=3x, CD=y \nAl1 AQ1D, P]Q2D, PzCD.Qj ~01.Qj tJ.oj 10 \nL'..AQ1D+ L'..P)QzD+ L'..PzCD= 6\n1 \nXY\n+ \n=~xY=10\n9 \n:. xy=10x 18 \n~ x \n2\n=18, 18X =Z7 \n:. x=3/3 (.: x>O) \nx\n2\n+qx+p=0.Qj \nkt'.}-a-}J?:! \nk\n2\n+pk+q=k\n2\n+qk+p, (p-q)=O \n(p-q)(k-1)=0 :. k=1 (': p*q) \nPS\" ~Zg at'.} \nolII1l, a ~ o17zPclJ?:j 61 \n=0.Qj -2', 3a~ Oj7,}BJ \n~61 x\n2\n+qx+P=0.Qj \n°1 \n7z\n}BJ?:j61.Qj -2'2j-Jl1",
      "solutionDisplay": "식 정리 후 x=10 형태를 이용한다.",
      "formulaLatex": [
        "x=10",
        "x=24",
        "Jx=10",
        "X=24L",
        "y=24",
        "y=10L",
        "Ai]E",
        "2x-2z=",
        "z=x+2",
        "CSP11",
        "Zx+y=ZO",
        "17cr",
        "6a+6b=1",
        "15a+5b",
        "10c=",
        "3a+b-Zc=",
        "1Za+",
        "1Zb-12c=1",
        "a+b-c=",
        "tj-a-",
        "3a+b=3i1",
        "Zx=3y",
        "AQ1DoJj",
        "AD=x",
        "CDoJ1",
        "P2D=3x",
        "CD=y",
        "AQ1D",
        "AQ1D+",
        "P)QzD+",
        "PzCD=",
        "xY=10",
        "xy=10x",
        "x=3/3",
        "qx+p=0",
        "pk+q=k",
        "qk+p",
        "p-q)=O",
        "p-q)(k-1)=0",
        "o17zPc1J",
        "qx+P=0",
        "2j-J11"
      ],
      "graphExpressions": [
        "y=24",
        "y=10L",
        "Zx+y=ZO",
        "xy=10x"
      ],
      "matched": true,
      "matchScore": 1
    },
    {
      "number": 12,
      "questionImage": "questions/06여러가지 방정식_q012.webp",
      "solutionRaw": "J­\n1+1=2 \nq1-2 a, \n13, \nr, \n~AR~cj-. ({J-) \n.:::Lt1~ \n\" L. c \n0\n1q. \n@@ \n~fj;I'i\\t~~Qj 2:i!f 711*.2.1 tJ:f71I~ olgolO1 a+13. a13.2.1 y~ \n-T'e!er. \n~Z{.gZ{i§Qj '3!\\1\"1£1 ~OPf 1~ ITH 1<£1 ih'Ol ~AHofi=AI '§i \noreer. \nZ{i§£1 '3!\\1\"1Qj ~OPr a !:fe 13~ ITH 1<.2.1 'lh'01 ~AHof \nAI ~'OfEer. \n(k+3)x-k=0.9.j A11 \n%~pclJAa61.9.j 7-l1~.9.j :t!-7-l1oJ1 \n.9.j-oj-6:J \n1 \nIxaxf3=k \n:. a+ 3, af3=k \n:. k=4 \nk=4iii \n%~j-rlJ~61oJ1 rH~-o}lfl \nx \n3\n-4x\n2\n+ \n(x-I) 3x+4) =0 \n1 .rf.~ x'-3x+4=0 \no1~j-rlJAa61 \nlfl D=( -3)2-4 X 4=-7<001.£.i-2. \n~q. \n(n) 3)z]-1[zrttl.9.J \t\n~01~ I, 13 \n(a+f3)(a-f3) 1, 3(a-f3)=1 C: \nf3=J... \n3 \n015!g S.9.J af3 \n\nk='i... x \n\n3 \n(ill) \n01q. \n.£ m=9, n=20 \n:. m+n=9+20=29 \n@ 29 \n)!j\"~6j~ \\1\"1i§of01 y2f zOlI cHe! 6j~ -T'e!et. \n'¥ 2££ i5fi= 01j:i1:!:t~6j!iif -T'~fCf. \nlJ. z7f ~*01E'£. ~~!iif OlgofOj xQj Y.2.I \\!I$f1~ rtfCf. \nxQj ~ISW~ -T'e! OI[HQj .11 \n2 \nf 2£1 y~-T'elq \ncQ% rH~-o}lfl \n......(9 \n9-x\n2\n+2yz=25-10x+x', 2yz= \n:. yz=x\n2\n-5x+8 \n10x+16 \n01 rlJ~61.9.J \ny, z7j-\t\nD",
      "solutionDisplay": "식 정리 후 1+1=2 형태를 이용한다.",
      "formulaLatex": [
        "1+1=2",
        "q1-2",
        "f71I",
        "o1go1O1",
        "a+13",
        "AHofi=AI",
        "k+3)x-k=0",
        "pc1JAa61",
        "7-11",
        "7-11oJ1",
        "Ixaxf3=k",
        "af3=k",
        "k=4iii",
        "j-r1J",
        "3x+4)",
        "x^2-3x+4=0",
        "j-r1JAa61",
        "3)2-4",
        "3)z]-1[zrtt1",
        "a+f3)(a-f3)",
        "3(a-f3)=1",
        "f3=J",
        "n=20",
        "m+n=9+20=29",
        "of01",
        "i5fi=",
        "O1gofOj",
        "2yz=25-10x+x^2",
        "2yz=",
        "yz=x",
        "5x+8",
        "10x+16",
        "z7j-"
      ],
      "graphExpressions": [],
      "matched": true,
      "matchScore": 1
    },
    {
      "number": 14,
      "questionImage": "questions/06여러가지 방정식_q014.webp",
      "solutionRaw": "x+y=4, z=4xy \n\nx+y=4 ~ oJ.Qj ?:j9.Qj i?Al-v-J (x, y);: \n\n.:Fi:iEJ1 \n\n±-tloJ1.2.i?oj4. \n\n:. z=4Xlx3=12 \n\n(1, 3), (Z, 1)\nx 3/3=Z/3 \n=10/3 \n\nabc+ab+bc+ca+a+b+c=290iP'1 \n1+abc+ab+bc+ca+a+b+c=29+1",
      "solutionDisplay": "식 정리 후 x+y=4 형태를 이용한다.",
      "formulaLatex": [
        "x+y=4",
        "z=4xy",
        "A1-v-J",
        "z=4X1x3=12",
        "3/3=Z/3",
        "abc+ab+bc+ca+a+b+c=290iP",
        "1+abc+ab+bc+ca+a+b+c=29+1"
      ],
      "graphExpressions": [
        "x+y=4"
      ],
      "matched": true,
      "matchScore": 1
    },
    {
      "number": 19,
      "questionImage": "questions/06여러가지 방정식_q019.webp",
      "solutionRaw": "1 ~ \n16 \na(a\n2\n-I) , I6a\n3\n-16a= \na\n3 \n-\na(a+4)(a-4) 0 \n\n:. a=4 C-: a>I) \n\nrrJ-2.}Ai 4° jq. \n\n~oI7} x mm'Z! -=jLQj ¥TIHj ~ \n(14-2x) mm \n3\ni7rX\n3\n+7rX\n2\n(14-2X) 1087r, -~ x  + 108=0 \nx\n3\n-21x\n2\n+ 162=0, (x-3) (x'-18x-54) =0 \n:. x=3 x=9±3[i5 \n~'tlI:ll O<x<7oj~ x=3 @3 \nx\n3\n+x'-x+2= ooJlJ.i (x+2) (x\n2 \n-\nx+1) =0 \n°d'~oJl x+",
      "solutionDisplay": "식 정리 후 16a= 형태를 이용한다.",
      "formulaLatex": [
        "16a=",
        "a(a+4)(a-4)",
        "14-2x)",
        "i7rX",
        "14-2X)",
        "108=0",
        "162=0",
        "x^2-18x-54)",
        "x^2-x+2="
      ],
      "graphExpressions": [],
      "matched": true,
      "matchScore": 1
    }
  ]
}