{
  "schemaVersion": "2.0",
  "sourceQuestionPdf": "\\\\Subitmainpc\\수학의 빛 사무폴더\\09.새 교과과정 자료\\02.자료_수학2\\교재_스캔(수학2)\\블랙라벨_수학2-PDF\\4지수와 로그\\09로그.pdf",
  "sourceAnswerPdf": "\\\\Subitmainpc\\수학의 빛 사무폴더\\09.새 교과과정 자료\\02.자료_수학2\\교재_스캔(수학2)\\블랙라벨_수학2-PDF\\4지수와 로그\\09로그_답안지.pdf",
  "curriculum": {
    "grade": "고2",
    "semester": "1학기",
    "course": "대수1",
    "unit": "지수로그",
    "score": 9
  },
  "difficulty": "하",
  "items": [
    {
      "number": 0,
      "questionImage": "questions/09로그_q000.webp",
      "solutionRaw": "15 \n\n= 0.30 c \n\n=-.lc\n2 \n.<:f-~ P(m. 17). Q(a, e)7f ZfZf ~-:':::i:i!f ~-:':::i ~Oil ~};Hg \n~ OI~ofOj -El1I16)~ 'i'-E!cf. \nlog AB9.j ~~ OI~ofOj AB£I ~1S!!~:i!f ~I:;t:~~ 'i'-E!~, \n~* k£1 ~~ 'i'-E!Cf. \n~ P(m, n)-.9..2l-l 1J=~ -'?-1oj1 Ol~",
      "solutionDisplay": "식 정리 후 e)7f 형태를 이용한다.",
      "formulaLatex": [
        "e)7f",
        "21-1"
      ],
      "graphExpressions": [],
      "matched": true,
      "matchScore": 1
    },
    {
      "number": 1,
      "questionImage": "questions/09로그_q001.webp",
      "solutionRaw": "=6n+2 \neln:Jl, \n(L]-)oJl-\"i f(a) + f(a\n2 \n) \nl4 \ne\nl£.? \n611+2=14, 6n=12 \n... n=2 \n(i), (li)oJVi log a=2+ \n\nlog a\n6\n=6log a=6(2+ \n\n15 \n... f(a\n6 \n)=15 @) 15 \n3 5H~8Jjl \n~-------------------------\n-1. T=O~ lIR \nlog 4.8=a+ c \n01n:Jl, log 4<log 4.8< log 50JH \n2 log 2< log 4.8< I-log 2 \n... 0.602< log 4.8<0,699 C-: log 2=0.301) \n~, 0.602<a+ c <0.699 (~) \nL. y=log T, y<>l] cJl{l-.:<f-*2.1~~ \nO::Il\"A _ b 01\n.? T, y<>l] \ntr'-·df, y-a+ c+1' ~ ....J.~II=·.-\n{l-cJ-. \n... b<O m) \n1:: \nT. yon cJl{l­\n\nlog P<a ... P< 10\" \n\non \nA\n1T> -c~.2.:=': il~ Ton \n5!;:, \" L, 1:: 0] L.}.",
      "solutionDisplay": "식 정리 후 6n+2 형태를 이용한다.",
      "formulaLatex": [
        "6n+2",
        "L]-)oJ1-i",
        "611+2=14",
        "6n=12",
        "61og",
        "a=6(2+",
        "I-1og",
        "y=1og",
        "1-cJ-"
      ],
      "graphExpressions": [
        "y=1og"
      ],
      "matched": true,
      "matchScore": 1
    },
    {
      "number": 2,
      "questionImage": "questions/09로그_q002.webp",
      "solutionRaw": "j-o-}It! \nlog l= -log y= -(n+{J)\ny \n\n=(-n-1)+(I-{J) \n\na=I-{J, \n3:Z:j (7J)Ol]Al log \nlog \nlogx+3logy \n=5n+2 \n=12,5 \n:. n=2, $=0.5 (\" . \n$=0.5~ <Q0l] cH'?Jo-}c9 a=0.5 \nrr}2.j-\nA\nl log x=log y=2+0.5=2.5\no\n]EJ£ \n5\nX 10\n2\n.\n-=--=1 \n@1\nY 10\n2\n.5 \n01 gXiE £::J.2l AII£5'.f 7~OJ\\il!lIl!~tH=AI~ c~ gXilOlq. \nx!;!.q .3J\\1 ?jg i.lcH£j ~~[xler 1I1l11, log x£j AllIe [log xl \n£, log x£j 7f\"ft log x-Dog xl.§!. LtEf'ii!! -* 'UCf. ~, gXilail)..l \n~{i (LI~ ~H log xSOf log y~ AlR7f ~.I1, ~{i (CI~ ~H log x \nSOf log }£j 7f\"f7f ~f[::H= ~~~-* 'Ucf. 01 gXil Q;j)..Il;{iOI m \nq!E!f.j !;!.OIAI'2.! ~%1~.2.!Ee £:J.l!~£j 71€-~ \n~q \n\"ri 11 aWOl 24\nA\n}212J \nC.:\"\"':_' , 23::; log aW< \n23::; 5log ab < 24 \n\n23::; 5 (log a+log b) < 24 \n\nlog ~: 2J A] \n,15 \n15::; 510g <16 \nb) 16 \nb<3.2 \n:. 3.8::; log a<4",
      "solutionDisplay": "식 정리 후 n-1)+(I- 형태를 이용한다.",
      "formulaLatex": [
        "n-1)+(I-",
        "7J)O1]A1",
        "1ogx+31ogy",
        "5n+2",
        "x=1og",
        "y=2+0",
        "tH=AI",
        "gXi1O1q",
        "x1er",
        "A11Ie",
        "7fft",
        "x-Dog",
        "gXi1ai1)",
        "A1R7f",
        "7ff7f",
        "gXi1",
        "aWO1",
        "51og",
        "a+1og",
        "510g"
      ],
      "graphExpressions": [
        "y=2+0"
      ],
      "matched": true,
      "matchScore": 1
    },
    {
      "number": 3,
      "questionImage": "questions/09로그_q003.webp",
      "solutionRaw": "_ 2(4a+b) \n-3(2a+b) \nlogz (lOg3 2) +  logz (lOg4 3) + log2 (logs 4) +  ... \n\n+logz (loglG 15) \n\n=  logz (logs 2 \nX 10g4 3 X logs 4 X ••• X logl6 15) \n\n=log, ( 12&; X 10.&1.. X lQgci. X ••. X log, 15 ) \n-log, J log, 4 log, 5 10K 16 \nc>O, \nlog, 2   \\ ( )\n( 16 ;1= log2 logl6 \n2 \n_\nI\noge \n1 \n4 \n=logz -2 \n@) -2 \nP10glO 30+10g:100 +4=Oojj\nA\n1 \np loglo 30+q loglon 9+4=0 \np 10glO 30+q 10glO' \nP(lOglO 3+ 1) +qloglO 3+4=0 \n(P+4) + (p+q)loglo 3=0 \n6Joj]Al p, %2.]9°1.Jl logj() \n¥2.],,?7t Al5'.. 3':-?loj] .2it>tO:J \nP+4=0, :. P=-4, q=4 \np= 1~ \tITll, 3, ''', 20 (l97};:Zj) \nITll, 6, \"', 20 (97};:Z]) \nITll, q=6, 9, 12,  15, 18 (57};:Z]) \n'iJ rrJl, 12, 16, 20 (47};:zD \nP=5~ ITll, q=10, 20 (37};:Z]) \nP=6'iJ ITll, q=12, 18 (27t;:z1l \nP=7'iJ ITll, q=14 (pt;:z]) \nITll. q=16 (p};:zl) \nITll, q=18 (P};:zll \n10~ ITll, q=20 (Pt;:z]) \nrrJ-cj-A1 78-9-.211\"::: 46 ° Jr:}. \n@) 46 \nlog A=n+a(n;:' .7-a\"?, O~a<l)cj-f;}1i'1 \nAa9\n0 \nj.Jl. 0~a2<1 \nn= (1= ~ (': 0~(1< 1) \n:. log A=3+i= .1:E::: log A=-3+~-= \nrrJ-cj-Al \n+(-@) \nIV. XI1'l'f.£:l I 081 \n\nl<l-a<1\n0 \n]Jl\n(7f)0111'i 0<a < \n2 ' \n(y.)01]Al log4 n= \nn<1 \n2< n<log44, 2< n<4 \n:. n=3 (\": \nlog, n =1-aOl] cH\":J5\"Pi'.l \n3=I-a \n4 1 3 I 4\n3= og1 4 + OR, 3 \nO]u:JL logz m\nZ\n=log2\" m'o]EJ£ \n4'\nlog; nl=loRI \n0J\\12J 5QQj ~o] 4£i£~ \n44 \n:. 3nl'=3 x ::I =4'=256 \n@ 256 \n~{:IILI)ail)..llog x=n+a, log y=n+!3 (ng ~-*, \nO:::;a<l, O::;!3<l)2.f~q. \n~{:Ilq)aiIAl log xSOf log l£j 7f-*7[ Al.~ ~OClS= \nY \na=l-!3, ~ a+!3=l~~ OlilH~q. \n\n~{:I (l!lail log X=I1+a, log y=n+!3~ [H'~~ l?:, n, a, \n\n!3£j ~~-T'-tf01 f 9.1 ~~-T'-~cf. \n3:Z:j (y.)c'ljAi log xQ)· log yQj AllE7} c~~ \nlogx=n+a,logy=n+$ \n(n:: 7a\"?, 0::; a<1, \n<1)",
      "solutionDisplay": "식 정리 후 2(4a+b) 형태를 이용한다.",
      "formulaLatex": [
        "2(4a+b)",
        "3(2a+b)",
        "1ogz",
        "1Og3",
        "1Og4",
        "1og2",
        "1ogs",
        "1og1G",
        "10g4",
        "1og16",
        "1Qgci",
        "P10g1O",
        "30+10g",
        "1og1o",
        "30+q",
        "1og1on",
        "9+4=0",
        "10g1O",
        "P(1Og1O",
        "q1og1O",
        "3+4=0",
        "p+q)1og1o",
        "1ogj()",
        "P+4=0",
        "q=10",
        "q=12",
        "q=14",
        "q=16",
        "q=18",
        "q=20",
        "78-9-",
        "A=n+a(n",
        "1)cj-f",
        "A=3+i=",
        "7f)0111",
        "01]A1",
        "1og4",
        "1og44",
        "1-aO1]",
        "3=I-a",
        "n1=1oRI",
        "IILI)ai1)",
        "11og",
        "x=n+a",
        "I1q)aiIA1",
        "7f-*7[",
        "OC1S=",
        "1ai1",
        "X=I1+a",
        "tf01",
        "1jAi",
        "A11E7",
        "1ogx=n+a",
        "1ogy=n+"
      ],
      "graphExpressions": [
        "1ogy=n+"
      ],
      "matched": true,
      "matchScore": 1
    },
    {
      "number": 4,
      "questionImage": "questions/09로그_q004.webp",
      "solutionRaw": "AJ-h(jj ~J1\\-~ BJ-A}{! Cfl7.tQj \n44 %0]1:f. \n-.----------~.... \n(2x+5)(5x\n2\n+4x+k)=OQj Ail \n5x\n2\n+4x+k=OQj f \nt \no]1:f. \nnJ1\\-°l~P\"J-?1~ 5x\n2\n+4x+k=OQj \n\noj~\\-BJ?16JQj tJ1\\-J.1]4'.9.J -¥fJ.1]o1] .9.J15t~ \n\nn+a=--.i=-l+\nl \n5 5 \n:. n= \n1 a=l \n, 5 \n090 I \n\n\n1 l2­\n,   5 a \nl)(X~ ~ )=001]A1 (x+1)(5x~1)=0 \n:. 5x\n2\n+4x-1=0 \n:. k= 1 \n(2) (l)o1]Al a= ~ , k= l0IE-.£. \n:J \n20k\n=( ~ rWa \n:. log 5\n10 \n=20 log 5 \n=20 log \n=20( 2) \n=20(1-0.3010) \n=20 X 0.6990 \n=13.98 \nu:}2}Al log a\n20k\nQj 13\no\njP.£. \n4'°lq. \n0113 024 032 \n0527 06150 \n10-2x-x\n2\n=1, x\n2\n+2x-9=0 \n:. x= 1 \n;::::a (l.1)oj]A1 log y= ~ + log (x+4) \nlog jT6+log H) \n=log [jT6(x+4) J \nlog y=log (jT6(x+4) JojjA] £.:LQj ~o] 10~ \ny=JlO(x+4) \n\n0] IT11, ;::::ao1j \nx+4>0, x> \n\n&>1]A-] \n\nx=-l+jT6 \n-1 \n=/10(3+J10) \n= 10 + 3jT6 \n:. y-3x=(10+3jT6) 3( -1+ \n=10+ 3/10 \n=13 \n13 \nxQi i:.tQI ~!fI~ l<x<lO,lOS:.,,<lOO, lOOS:x<lOOO, \n1000 s: xS: 2014.5!. Lf!r(}j ~:z.ti2:.li:f. \n• '2!'7iIQJ :z.t ~!fIOII.A.l [log x), r -10~ x ]Qi i:.t~ 'l'-i'ifOj \ngj* f(x)QJ j:1\"'l~ 'l'-\\!fCf. \nf(x) x][ ­\n(i) 1<x<10'?J uJl, \n[log \nf(x)=o \n(li) 10::;x< 100'?J uJl, \n[log x]=l, [ \nf(x)=l X  ( 1)=-1 \n(iii) \t100 ::;x< 1000'?J IT11, \n[log \n[­\n-2 \n(iv) 1000::;x::;2014'?J IT11. \n[log [IO~X \nf(x) x(-1)=-3 \n(i)~(iv)ojIAi\"ij-4' f(x)Qj j.jQ:jt {-3, \n-l,Ojo]q. \nu:}2.}\nA\nl .::r-\"'H=-4\no\njq. \n@4 \n6JQj 0J~ojj tt\"'~1i'1 \n2log\n5 \n~4+... \n2\n3 \no]IT11. 0<log5 4<l\no\njP.£. b1=0 \n4'= logs 16 \n~+ +... \n2 \n1<log516< b,=l \nb\n3 \nb. ]\nlog516=1+Z+?+\"'o P.£. \nN. S!..::l I 091 \n\n-------------------------------\nloge 16-1=logs 5\n16 \n='2+~+... \n2 2' \n\n@9.1 0JI(!oj1 2 ~ ~\"5}tB \n\n16 256\n\n2logs 5 =  logs ~ \n=b3+~+ b~ +... \n2 2­\n5\n6\n°1rrJ1, l<logs 22\n5<2°1.!::'..£ \nb\n3\n=1 \n.\". b\n1\n+b\n2\n+b\n3\n=0+1 + 1=2 \n01 g};iiE g};il <';H~£I OfOICI0j7f .gcdOl };HDI'1!e g};iIOICf. ~~",
      "solutionDisplay": "식 정리 후 AJ-h(jj 형태를 이용한다.",
      "formulaLatex": [
        "AJ-h(jj",
        "BJ-A",
        "Cf17",
        "2x+5)(5x",
        "4x+k)=OQj",
        "4x+k=OQj",
        "001]A1",
        "x+1)(5x",
        "4x-1=0",
        "1)o1]A1",
        "10IE-",
        "20(1-0",
        "10-2x-x",
        "2x-9=0",
        "jT6+1og",
        "jT6(x+4)",
        "y=1og",
        "y=J1O(x+4)",
        "ao1j",
        "x=-1+jT6",
        "10(3+J10)",
        "y-3x=(10+3jT6)",
        "f(x)QJ",
        "f(x)=o",
        "f(x)=1",
        "x(-1)=-3",
        "f(x)Qj",
        "21og",
        "1og5",
        "b1=0",
        "1ogs",
        "1og516",
        "1og516=1+Z+",
        "1oge",
        "16-1=1ogs",
        "0JI(",
        "21ogs",
        "OfOICI0j7f",
        "gcdO1"
      ],
      "graphExpressions": [
        "y=1og",
        "y=J1O(x+4)",
        "f(x)=o",
        "f(x)=1"
      ],
      "matched": true,
      "matchScore": 1
    },
    {
      "number": 6,
      "questionImage": "questions/09로그_q006.webp",
      "solutionRaw": "01 ~~I0f71 IIllgojl \"'~<';H .\"2.~ * '1!;>::I~ b\nk\n7f 0 .'Ee 1'2.l ?';!Oil \n:&«>JtfOj *~ [~~]9.j gt9.j ~e.i()1 O.\"2.q 3..:il l.\"2.q <S,lQfAi 7f*9.j \nQl~~ g~ IIf~fE ?,;!Ol %RtfCf. Ol~ OI<';HE!~, ~\\!'!Oil 2~ ~~ \nofOj is\"ofOj '?-\\!'!~ (;>::IR)+(7f*)~.£ ~2.lofE ~Ol ~Rofq. \nfRl. ND\n\\lJ!9'\n..i 5H~87jl \n~6:j01 ~il.§ ;>::1 k\\:l0l £I~~ rrH .\"lEI@-40£1 ~Ol OfE. \n-2-40£1 ~£I 20~H7f .<g~ OI~ofOj k2f cOil [HE! 6)~ 'i'­\nE!Cf. \nlog 1.415. log 29.j ~~ OI~ofOj k9.j ~~ 'i'-E!Cf. \n~~o1 l-~l-d-'8 A1 k\\1°1 501:d~ rrJ1 R=.%-409.1 0Jo1 \no}~~-409.1 0J9.1 20 \n1l\nH7} 501:d~ \nP(k) =20A(k) oj1l-l \n2\"=[1+83 \nX \nA(k) ]C \n. 20A(!?) \n1\n=(1+8.3 X 20)' \n= 1.415\nc \n-'?-19.1 0.19.1 °Jl(!oj1 AJ%.£~~ ~\"5}tB \n\nk log 2 =c log 1.415 \n\nk= log 1.415 c \n\nlog 2",
      "solutionDisplay": "식 정리 후 I0f71 형태를 이용한다.",
      "formulaLatex": [
        "I0f71",
        "1QfAi",
        "7f*9",
        "IR)+(7f*)",
        "1ofE",
        "1EI-40",
        "2-40",
        "cOi1",
        "20A(k)",
        "2=[1+83",
        "20A("
      ],
      "graphExpressions": [],
      "matched": true,
      "matchScore": 1
    },
    {
      "number": 9,
      "questionImage": "questions/09로그_q009.webp",
      "solutionRaw": "J \t~~.2l~.i!} \nlV. XI+2, = I 089 \n\n~§~AI!L2I ll<i'£l ~~~ ~DfLr ~~Wll ol%llot.J1: 2leA~ \n~lfiii{::-%R~ ~xil5 ~xij.QI ~l:!OI .QjDliii{::-U~:J.~ UfE. \n/II LfEf';i! *2li:-AI£ ~lfWIIIll@Ol1 OF, ~g~x;IOlq. \n011Ill, ~x;lijB~.Qj 'i!~e log m=2+x, log .n=2+y, \nlog mn=4+c (x, y,ce 1,*)~.J1: ~zFoi{::-~olq. \nlog mn=log m+log n=4+x+yOfIA; x, y, x+ylf £.!j' ll<i' \nOl£§l O:S;x<l, O:S;y<l, O:S;x+y<l'El~lIf\"-W-*, ~ \n~~E~\\!! ~Ofl LfEfLHi:-3101 %RiifCf. \nlog 6\n3\n°=30 log 6= 30(log 2+log 3) \n=30( 0.3010+0,4771) \n=23.3430 \n'. log 63(JQj 7.]1E7\\-23 \n0\n]-'::1-5'.. 6\n30 \n~ 247.r2.1Qj \nL. \t-log 6\n30 \n=  -23.3430 \n=-24+0.6570 \n=24.6570 \n.-. [-log 6\n30\n]=-24 \nc. log 2=0.30lO, log \nlog 2<0.3430< log 3 \n23+log 2<23+0.3430< 3 \nlog (2 X 10\n23 \n) <  23.3430 < log (3 x \nlog (2 X 10\n23\n) < log 6\n3\n°< log (3 X 10\n23 \n) \n'-.2x1023<630<3x1023 \n\nu:}ttAl 630 Qj ~2 \n~J) \n\n.::L21E..£. fg~ :;J,~ \" CO]e}. \nA, B7.]~Qj :i::2.]Qj \nQj :i::2.1Qj }.i]7]7t B7.]~Qj \n=500P\nB \n...... (JlP \nA \n.!E~, A, B7.]~Qj \nDj\\=10 log \n=10 log \n=10 (lOg \n10 \nlog \n=  10 log -'=-;;:-IL (\".­\n=10 log 500 \n10 log \n=10(3-log2) \n\n=10(3-0.3010) \n\n=26.99(dB) \n@ 26.99 dB \n\n30°C~ u:jJQj \nh %0]2 ~:r§-F7].g.o] \n~~~X 1.05\n3\n°= h~465 X 1.05\n5 \n/z-65\nX \n14 \n7 \nX 1.05\n25\n=h-65 \n\n:. h=65+7 X 1.\n05\n25 ......6) \n\noju:jJ, \n\nlog 1.05\n25 \n=25 X log 1.05 \n\n=25x 0.021 \n=0.525=log 3.35 \nlog 1.05\n25 \n=log 3.3501jJ,l 0J~Qj \n.2..-'::1.£",
      "solutionDisplay": "식 정리 후 XI+2 형태를 이용한다.",
      "formulaLatex": [
        "XI+2",
        "21eA",
        "1fiii",
        "xi15",
        "1fWIII11O11",
        "1ijB",
        "m=2+x",
        "n=2+y",
        "mn=4+c",
        "mn=1og",
        "m+1og",
        "n=4+x+yOfIA",
        "x+y1f",
        "1If-W-*",
        "30(1og",
        "2+1og",
        "3010+0",
        "63(JQj",
        "24+0",
        "23+1og",
        "23+0",
        "2x1023",
        "3x1023",
        "ttA1",
        "CO]e",
        "10(3-1og2)",
        "10(3-0",
        "99(dB)",
        "z-65",
        "h-65",
        "h=65+7",
        "525=1og"
      ],
      "graphExpressions": [],
      "matched": true,
      "matchScore": 1
    },
    {
      "number": 12,
      "questionImage": "questions/09로그_q012.webp",
      "solutionRaw": "J­\n1\nZ(log\" 2+ 10gb 2) \n1+ \nX(­\n1 \n3 \nlV. Xl?£' S'.=! I 085 \n\n[J)~ 1 ~x~9'?J rrJ1, \n0~log10 x< 1°1~ [IagIo xJ=O \n10~x~99'?J rrJl, \nl~loglo x<2°1~ [loglo xJ=l \n\n100~x~999'?J rrJ1, \n\n2~logl0 x<301~ [loglo xJ=2 \n\n1000~x~2014'?J rrJ1, \n\n3~logl0 x<4°1~ [lOgIO xJ=3 \n\n:, /(l) +/(2) +/(3) +\"'+/(2014) \n\n=0 x 9+ 1 x 90+2 x 900+3 x  1015 \n=0+90+ 1800+3045=4935 \n® 4935 \n0\\'lirc= log AQj A1lt.~ n, 7}~~ ac.} o}1i'!\n,'=V~ \nlog A=n+a (t!, n~ 1l4-, O~a<1) \n\n'. log 10A=log 10+1og A \n\n=1 + (n+a) = (n+1) +a \n\n~, log 10AQj 7}1';: a \n0\n1L}. \n\nL. log A \n10\n=10 log A=10(n+a)=10n+10a01~ \nlog A10Qj 7}1';: 10a-[10aJ\n0\n1\nL}. \n10\nc.log A=log 10-1og A \n=1-(n+a) = -n+(l-a) \n10 \n~, log AQj 7}1';: I-a (O<a<l) 3:.;: 001L}. \nrr}c.}Al log AQj 7}4-Q}7}4-7} ~~\"\"J-%.5Q;: ,01L}. \n@CD \ntmIiD \nL. (~?jD a= ~ 011i'! log A \n10 \n=10n+10a=10n+5°1 \n~log AlOQj 7}1';: 001L}. (7~:m \nc. (Jt}r;jD a= ~ 011i'! \n10 ( 2 10\nI\nog A=-n+ 1-a)=-n+301~ log A \nQj 711';: ~ 01L}. (71:m \n10\n(Q)~ log 6°=100 log 6= 100 (log 2+1og 3) \n=  100(",
      "solutionDisplay": "식 정리 후 Z(1og 형태를 이용한다.",
      "formulaLatex": [
        "Z(1og",
        "10gb",
        "1og10",
        "xJ=O",
        "1og1o",
        "xJ=1",
        "xJ=2",
        "1OgIO",
        "xJ=3",
        "90+2",
        "900+3",
        "0+90+",
        "1800+3045=4935",
        "1irc=",
        "A11t",
        "A=n+a",
        "114-",
        "10A=1og",
        "10+1og",
        "10AQj",
        "A=10(n+a)=10n+10a01",
        "A10Qj",
        "10a-[10aJ",
        "A=1og",
        "10-1og",
        "1-(n+a)",
        "n+(1-a)",
        "10n+10a=10n+5",
        "A1OQj",
        "1-a)=-n+301",
        "2+1og",
        "100("
      ],
      "graphExpressions": [],
      "matched": true,
      "matchScore": 1
    },
    {
      "number": 82,
      "questionImage": "questions/09로그_q082.webp",
      "solutionRaw": "4 k\n\n( \n100 = 100 \n~Qj ~.9.J 0J~o1] \"'...,..0.,-,= \n( \n82 \n)4\nlog \\  100 \n82 \n4 log 100 \n4(Iog 8.2-1) \nk-2 \n4(0.91-1) \nk-2 \n-0.36=log k-2 \n:. log k=1.64 \n0]u:jJ, log",
      "solutionDisplay": "식 정리 후 4(Iog 형태를 이용한다.",
      "formulaLatex": [
        "4(Iog",
        "91-1)",
        "36=1og"
      ],
      "graphExpressions": [],
      "matched": true,
      "matchScore": 1
    }
  ]
}