{
  "title": "[통합숙제] 수학1 - 삼각함수 그래프 16번 명품 해설",
  "type": "trigonometry",
  "P": "삼각함수의 그래프 변환(주기, 진폭, 위상)을 분석합니다.",
  "C": "기본 그래프에서 평행이동, 대칭, 주기 변환을 단계적으로 적용합니다.",
  "B": "삼각함수 그래프:\n\n1) $$y = a\\sin(bx + c) + d$$: 진폭 $$|a|$$, 주기 $$\\frac{2\\pi}{|b|}$$, 위상 $$-\\frac{c}{b}$$, 수직이동 $$d$$\n2) $$\\sin$$의 주기: $$2\\pi$$, $$\\tan$$의 주기: $$\\pi$$\n3) $$\\sin(-\\theta) = -\\sin\\theta$$ (기함수), $$\\cos(-\\theta) = \\cos\\theta$$ (우함수)",
  "S": "[단계별 풀이 흐름]\n아래 선생님의 정밀 판서 및 해설 이미지를 정독하여 논리 전개 과정을 완벽히 마스터하세요.",
  "S_objects": [
    {
      "type": "image",
      "src": "/math_crops/숙제/수학1/06삼각함수그래프/016a.webp"
    }
  ],
  "A": "따라서 최종 정답은 $$\\mathbf{\\boxed{1/3}}$$ 입니다.",
  "finalAnswer": "1/3",
  "correctAnswer": "1/3",
  "pcbsa_completed": true
}